slonk/__init__.py
slonk-0.1.1.dist-info/METADATA
slonk-0.1.1.dist-info/WHEEL
slonk-0.1.1.dist-info/RECORD
