Metadata-Version: 2.3
Name: slonk
Version: 0.1.1
Summary: Experiment in typed pipelining of data between python, shell and various data sources and sinks.
Author-email: Matt Oates <mattoates+support@gmail.com>
Requires-Python: >=3.8
Requires-Dist: cloudpathlib>=0.18.1
Requires-Dist: sqlalchemy>=2.0.32
